poketnas/__init__.py
poketnas/pokemon.csv
poketnas/random_pokemon.py
poketnas-1.0.0.dist-info/METADATA
poketnas-1.0.0.dist-info/WHEEL
poketnas-1.0.0.dist-info/top_level.txt
poketnas-1.0.0.dist-info/RECORD
